{
  "ts": "2026-05-25T22:54:51.051381+09:00",
  "start_date": "2026-05-25",
  "status": "running",
  "equity": 6678.72,
  "available": 3836.75,
  "unrealized": 14.87,
  "daily_pnl": -68.06,
  "total_pnl": -21.28,
  "cum_pct": -0.32,
  "daily_avg_pct": -0.32,
  "annual_pct": -68.96,
  "mdd": -1.5,
  "current_dd": -0.96,
  "seed_used": 2841.98,
  "seed_used_pct": 42.55,
  "long_count": 4,
  "short_count": 2,
  "positions": [
    {
      "symbol": "TONUSDT",
      "side": "SHORT",
      "pnl": -32.21,
      "pnl_pct": -1.37,
      "margin": 475.11,
      "leverage": "5",
      "tier": "2/2",
      "entry": 1.8078,
      "mark": 1.8327
    },
    {
      "symbol": "WLDUSDT",
      "side": "SHORT",
      "pnl": 16.55,
      "pnl_pct": 0.5,
      "margin": 473.59,
      "leverage": "7",
      "tier": "2/2",
      "entry": 0.3048,
      "mark": 0.3033
    },
    {
      "symbol": "HYPEUSDT",
      "side": "LONG",
      "pnl": 9.13,
      "pnl_pct": 1.16,
      "margin": 158.87,
      "leverage": "5",
      "tier": "2/2",
      "entry": 62.516,
      "mark": 63.243
    },
    {
      "symbol": "ZECUSDT",
      "side": "LONG",
      "pnl": 13.54,
      "pnl_pct": 1.75,
      "margin": 157.29,
      "leverage": "5",
      "tier": "2/2",
      "entry": 660.62,
      "mark": 672.19
    },
    {
      "symbol": "XRPUSDT",
      "side": "LONG",
      "pnl": 0.46,
      "pnl_pct": 0.06,
      "margin": 157.21,
      "leverage": "5",
      "tier": "2/2",
      "entry": 1.3563,
      "mark": 1.3571
    },
    {
      "symbol": "ONDOUSDT",
      "side": "LONG",
      "pnl": 7.42,
      "pnl_pct": 2.38,
      "margin": 79.81,
      "leverage": "4",
      "tier": "2/2",
      "entry": 0.4289,
      "mark": 0.4391
    }
  ],
  "signals": {
    "HYPEUSDT": {
      "dir": "long",
      "conf": 0.487
    },
    "WLDUSDT": {
      "dir": "short",
      "conf": 0.525
    },
    "ETHUSDT": {
      "dir": "neutral",
      "conf": 0.574
    },
    "XRPUSDT": {
      "dir": "long",
      "conf": 0.359
    },
    "TONUSDT": {
      "dir": "short",
      "conf": 0.435
    },
    "BTCUSDT": {
      "dir": "neutral",
      "conf": 0.362
    },
    "1000PEPEUSDT": {
      "dir": "long",
      "conf": 0.437
    },
    "ONDOUSDT": {
      "dir": "long",
      "conf": 0.423
    },
    "NEARUSDT": {
      "dir": "long",
      "conf": 0.379
    },
    "SUIUSDT": {
      "dir": "short",
      "conf": 0.432
    },
    "ZECUSDT": {
      "dir": "long",
      "conf": 0.489
    },
    "SOLUSDT": {
      "dir": "short",
      "conf": 0.433
    },
    "DOGEUSDT": {
      "dir": "long",
      "conf": 0.437
    }
  },
  "equity_hist": [
    {
      "t": "2026-05-25",
      "v": -21.28
    }
  ],
  "trade_history": [
    {
      "ts": "2026-05-25 20:15",
      "symbol": "NEARUSDT",
      "side": "Buy",
      "pnl": 33.76,
      "reason": "External Exit"
    },
    {
      "ts": "2026-05-25 17:48",
      "symbol": "WLDUSDT",
      "side": "Sell",
      "pnl": -101.81,
      "reason": "External Exit"
    }
  ],
  "num_days": 1
}