{
  "ts": "2026-05-25T20:35:41.093881+09:00",
  "start_date": "2026-05-25",
  "status": "running",
  "equity": 6696.43,
  "available": 5276.24,
  "unrealized": 31.65,
  "daily_pnl": -68.06,
  "total_pnl": -3.57,
  "cum_pct": -0.05,
  "daily_avg_pct": -0.05,
  "annual_pct": -16.69,
  "mdd": -1.5,
  "current_dd": -0.93,
  "seed_used": 1420.19,
  "seed_used_pct": 21.21,
  "long_count": 2,
  "short_count": 1,
  "positions": [
    {
      "symbol": "WLDUSDT",
      "side": "SHORT",
      "pnl": 16.55,
      "pnl_pct": 0.5,
      "margin": 473.59,
      "leverage": "7",
      "tier": "2/2",
      "entry": 0.3048,
      "mark": 0.3033
    },
    {
      "symbol": "HYPEUSDT",
      "side": "LONG",
      "pnl": 9.32,
      "pnl_pct": 1.19,
      "margin": 158.9,
      "leverage": "5",
      "tier": "2/2",
      "entry": 62.516,
      "mark": 63.258
    },
    {
      "symbol": "ZECUSDT",
      "side": "LONG",
      "pnl": 5.8,
      "pnl_pct": 0.75,
      "margin": 155.75,
      "leverage": "5",
      "tier": "2/2",
      "entry": 660.62,
      "mark": 665.58
    }
  ],
  "signals": {
    "HYPEUSDT": {
      "dir": "long",
      "conf": 0.487
    },
    "WLDUSDT": {
      "dir": "short",
      "conf": 0.54
    },
    "ETHUSDT": {
      "dir": "neutral",
      "conf": 0.62
    },
    "XRPUSDT": {
      "dir": "long",
      "conf": 0.356
    },
    "TONUSDT": {
      "dir": "short",
      "conf": 0.459
    },
    "BTCUSDT": {
      "dir": "neutral",
      "conf": 0.353
    },
    "1000PEPEUSDT": {
      "dir": "long",
      "conf": 0.439
    },
    "ONDOUSDT": {
      "dir": "short",
      "conf": 0.521
    },
    "NEARUSDT": {
      "dir": "long",
      "conf": 0.379
    },
    "SUIUSDT": {
      "dir": "short",
      "conf": 0.428
    },
    "ZECUSDT": {
      "dir": "long",
      "conf": 0.489
    },
    "SOLUSDT": {
      "dir": "neutral",
      "conf": 0.508
    },
    "DOGEUSDT": {
      "dir": "long",
      "conf": 0.438
    }
  },
  "equity_hist": [
    {
      "t": "2026-05-25",
      "v": -3.57
    }
  ],
  "trade_history": [
    {
      "ts": "2026-05-25 20:15",
      "symbol": "NEARUSDT",
      "side": "Buy",
      "pnl": 33.76,
      "reason": "External Exit"
    },
    {
      "ts": "2026-05-25 17:48",
      "symbol": "WLDUSDT",
      "side": "Sell",
      "pnl": -101.81,
      "reason": "External Exit"
    }
  ],
  "num_days": 1
}